Vald_Dashboard_API/ValdDashboardAPI.py
Vald_Dashboard_API/__init__.py
vald_dashboard_api-0.0.3.dist-info/METADATA
vald_dashboard_api-0.0.3.dist-info/WHEEL
vald_dashboard_api-0.0.3.dist-info/top_level.txt
vald_dashboard_api-0.0.3.dist-info/RECORD
